guard_exception/__init__.py
guard_exception-1.1.0.dist-info/LICENSE
guard_exception-1.1.0.dist-info/WHEEL
guard_exception-1.1.0.dist-info/METADATA
guard_exception-1.1.0.dist-info/RECORD
